<?xml version="1.0" encoding="utf-8"?>
<TextureAtlas imagePath="PLUNGER_Dialogue.png">
	<!-- Created with Adobe Animate version 21.0.0.35450 -->
	<!-- http://www.adobe.com/products/animate.html -->
	<SubTexture name="Plunger Angry0000" x="10" y="10" width="178" height="327"/>
	<SubTexture name="Plunger Angry0001" x="10" y="10" width="178" height="327"/>
	<SubTexture name="Plunger Angry0002" x="198" y="10" width="178" height="327"/>
	<SubTexture name="Plunger Angry0003" x="198" y="10" width="178" height="327"/>
	<SubTexture name="Plunger Angry0004" x="386" y="10" width="178" height="327"/>
	<SubTexture name="Plunger Angry0005" x="386" y="10" width="178" height="327"/>
	<SubTexture name="Plunger Angry Talk0000" x="10" y="10" width="178" height="327" frameX="0" frameY="-46" frameWidth="178" frameHeight="327"/>
	<SubTexture name="Plunger Angry Talk0001" x="10" y="10" width="178" height="327" frameX="0" frameY="-46" frameWidth="178" frameHeight="327"/>
	<SubTexture name="Plunger Angry Talk0002" x="574" y="10" width="178" height="374"/>
	<SubTexture name="Plunger Angry Talk0003" x="574" y="10" width="178" height="374"/>
	<SubTexture name="Plunger Angry Talk0004" x="762" y="10" width="178" height="356" frameX="0" frameY="-18" frameWidth="178" frameHeight="374"/>
	<SubTexture name="Plunger Angry Talk0005" x="762" y="10" width="178" height="356" frameX="0" frameY="-18" frameWidth="178" frameHeight="374"/>
	<SubTexture name="Plunger Cool0000" x="950" y="10" width="178" height="327"/>
	<SubTexture name="Plunger Cool Talk0000" x="950" y="10" width="178" height="327" frameX="0" frameY="-46" frameWidth="178" frameHeight="327"/>
	<SubTexture name="Plunger Cool Talk0001" x="950" y="10" width="178" height="327" frameX="0" frameY="-46" frameWidth="178" frameHeight="327"/>
	<SubTexture name="Plunger Cool Talk0002" x="1138" y="10" width="178" height="374"/>
	<SubTexture name="Plunger Cool Talk0003" x="1138" y="10" width="178" height="374"/>
	<SubTexture name="Plunger Cool Talk0004" x="1326" y="10" width="178" height="356" frameX="0" frameY="-18" frameWidth="178" frameHeight="374"/>
	<SubTexture name="Plunger Cool Talk0005" x="1326" y="10" width="178" height="356" frameX="0" frameY="-18" frameWidth="178" frameHeight="374"/>
	<SubTexture name="Plunger Dialogue Spooky0000" x="1514" y="10" width="250" height="339" frameX="0" frameY="-7" frameWidth="293" frameHeight="347"/>
	<SubTexture name="Plunger Dialogue Spooky0001" x="1514" y="10" width="250" height="339" frameX="0" frameY="-7" frameWidth="293" frameHeight="347"/>
	<SubTexture name="Plunger Dialogue Spooky0002" x="1774" y="10" width="255" height="328" frameX="-10" frameY="-18" frameWidth="293" frameHeight="347"/>
	<SubTexture name="Plunger Dialogue Spooky0003" x="1774" y="10" width="255" height="328" frameX="-10" frameY="-18" frameWidth="293" frameHeight="347"/>
	<SubTexture name="Plunger Dialogue Spooky0004" x="10" y="394" width="223" height="302" frameX="-53" frameY="-45" frameWidth="293" frameHeight="347"/>
	<SubTexture name="Plunger Dialogue Spooky0005" x="10" y="394" width="223" height="302" frameX="-53" frameY="-45" frameWidth="293" frameHeight="347"/>
	<SubTexture name="Plunger Dialogue Spooky0006" x="243" y="394" width="221" height="328" frameX="-53" frameY="-18" frameWidth="293" frameHeight="347"/>
	<SubTexture name="Plunger Dialogue Spooky0007" x="243" y="394" width="221" height="328" frameX="-53" frameY="-18" frameWidth="293" frameHeight="347"/>
	<SubTexture name="Plunger Dialogue Spooky0008" x="474" y="394" width="218" height="346" frameX="-75" frameY="0" frameWidth="293" frameHeight="347"/>
	<SubTexture name="Plunger Dialogue Spooky0009" x="474" y="394" width="218" height="346" frameX="-75" frameY="0" frameWidth="293" frameHeight="347"/>
	<SubTexture name="Plunger Dialogue Spooky0010" x="702" y="394" width="210" height="328" frameX="-75" frameY="-18" frameWidth="293" frameHeight="347"/>
	<SubTexture name="Plunger Dialogue Spooky0011" x="702" y="394" width="210" height="328" frameX="-75" frameY="-18" frameWidth="293" frameHeight="347"/>
	<SubTexture name="Plunger Dialogue Spooky0012" x="10" y="394" width="223" height="302" frameX="-53" frameY="-45" frameWidth="293" frameHeight="347"/>
	<SubTexture name="Plunger Dialogue Spooky0013" x="10" y="394" width="223" height="302" frameX="-53" frameY="-45" frameWidth="293" frameHeight="347"/>
	<SubTexture name="Plunger Dialogue Spooky0014" x="243" y="394" width="221" height="328" frameX="-53" frameY="-18" frameWidth="293" frameHeight="347"/>
	<SubTexture name="Plunger Dialogue Spooky0015" x="243" y="394" width="221" height="328" frameX="-53" frameY="-18" frameWidth="293" frameHeight="347"/>
	<SubTexture name="Plunger Miss0000" x="922" y="394" width="182" height="327"/>
	<SubTexture name="Plunger Miss0001" x="922" y="394" width="182" height="327"/>
	<SubTexture name="Plunger Miss0002" x="1114" y="394" width="182" height="327"/>
	<SubTexture name="Plunger Miss0003" x="1114" y="394" width="182" height="327"/>
	<SubTexture name="Plunger Miss Talk0000" x="1306" y="394" width="183" height="327" frameX="-1" frameY="-46" frameWidth="184" frameHeight="374"/>
	<SubTexture name="Plunger Miss Talk0001" x="1306" y="394" width="183" height="327" frameX="-1" frameY="-46" frameWidth="184" frameHeight="374"/>
	<SubTexture name="Plunger Miss Talk0002" x="1499" y="394" width="184" height="374"/>
	<SubTexture name="Plunger Miss Talk0003" x="1499" y="394" width="184" height="374"/>
	<SubTexture name="Plunger Miss Talk0004" x="1693" y="394" width="184" height="358" frameX="0" frameY="-16" frameWidth="184" frameHeight="374"/>
	<SubTexture name="Plunger Miss Talk0005" x="1693" y="394" width="184" height="358" frameX="0" frameY="-16" frameWidth="184" frameHeight="374"/>
	<SubTexture name="Plunger Nerveous0000" x="10" y="778" width="178" height="327"/>
	<SubTexture name="Plunger Nerverous Talk0000" x="10" y="778" width="178" height="327" frameX="0" frameY="-46" frameWidth="178" frameHeight="327"/>
	<SubTexture name="Plunger Nerverous Talk0001" x="10" y="778" width="178" height="327" frameX="0" frameY="-46" frameWidth="178" frameHeight="327"/>
	<SubTexture name="Plunger Nerverous Talk0002" x="198" y="778" width="178" height="374"/>
	<SubTexture name="Plunger Nerverous Talk0003" x="198" y="778" width="178" height="374"/>
	<SubTexture name="Plunger Nerverous Talk0004" x="386" y="778" width="178" height="356" frameX="0" frameY="-18" frameWidth="178" frameHeight="374"/>
	<SubTexture name="Plunger Nerverous Talk0005" x="386" y="778" width="178" height="356" frameX="0" frameY="-18" frameWidth="178" frameHeight="374"/>
	<SubTexture name="Plunger Normal0000" x="574" y="778" width="178" height="327" frameX="0" frameY="0" frameWidth="178" frameHeight="374"/>
	<SubTexture name="Plunger Normal Talk 0000" x="574" y="778" width="178" height="327" frameX="0" frameY="-46" frameWidth="178" frameHeight="374"/>
	<SubTexture name="Plunger Normal Talk 0001" x="574" y="778" width="178" height="327" frameX="0" frameY="-46" frameWidth="178" frameHeight="374"/>
	<SubTexture name="Plunger Normal Talk 0002" x="762" y="778" width="178" height="374"/>
	<SubTexture name="Plunger Normal Talk 0003" x="762" y="778" width="178" height="374"/>
	<SubTexture name="Plunger Normal Talk 0004" x="950" y="778" width="178" height="356" frameX="0" frameY="-18" frameWidth="178" frameHeight="374"/>
	<SubTexture name="Plunger Normal Talk 0005" x="950" y="778" width="178" height="356" frameX="0" frameY="-18" frameWidth="178" frameHeight="374"/>
</TextureAtlas>
